loadconf/__init__.py
loadconf/loadconf.py
loadconf-0.0.13.dist-info/LICENSE.md
loadconf-0.0.13.dist-info/METADATA
loadconf-0.0.13.dist-info/WHEEL
loadconf-0.0.13.dist-info/top_level.txt
loadconf-0.0.13.dist-info/RECORD
