Metadata-Version: 2.1
Name: loadconf
Version: 0.0.13
Summary: Give users an easy way to define settings and personalize their use of your program.
License: GNU General Public License v3 (GPLv3)
Project-URL: repository, https://codeberg.org/johndovern/loadconf
Keywords: shell,scripting
License-File: LICENSE.md
